LICENSE
MANIFEST.in
NOTICE
README.md
requirements.txt
setup.cfg
setup.py
compiler/__init__.py
compiler/api/__init__.py
compiler/api/compiler.py
compiler/api/source/auth_key.tl
compiler/api/source/main_api.tl
compiler/api/source/sys_msgs.tl
compiler/api/template/combinator.txt
compiler/api/template/type.txt
compiler/errors/__init__.py
compiler/errors/compiler.py
compiler/errors/sort.py
compiler/errors/source/303_SEE_OTHER.tsv
compiler/errors/source/400_BAD_REQUEST.tsv
compiler/errors/source/401_UNAUTHORIZED.tsv
compiler/errors/source/403_FORBIDDEN.tsv
compiler/errors/source/406_NOT_ACCEPTABLE.tsv
compiler/errors/source/420_FLOOD.tsv
compiler/errors/source/500_INTERNAL_SERVER_ERROR.tsv
compiler/errors/source/503_SERVICE_UNAVAILABLE.tsv
compiler/errors/template/class.txt
compiler/errors/template/sub_class.txt
pyroge/__init__.py
pyroge/client.py
pyroge/dispatcher.py
pyroge/emoji.py
pyroge/file_id.py
pyroge/filters.py
pyroge/mime_types.py
pyroge/py.typed
pyroge/sync.py
pyroge/utils.py
pyroge.egg-info/PKG-INFO
pyroge.egg-info/SOURCES.txt
pyroge.egg-info/dependency_links.txt
pyroge.egg-info/not-zip-safe
pyroge.egg-info/requires.txt
pyroge.egg-info/top_level.txt
pyroge/connection/__init__.py
pyroge/connection/connection.py
pyroge/connection/transport/__init__.py
pyroge/connection/transport/tcp/__init__.py
pyroge/connection/transport/tcp/tcp.py
pyroge/connection/transport/tcp/tcp_abridged.py
pyroge/connection/transport/tcp/tcp_abridged_o.py
pyroge/connection/transport/tcp/tcp_full.py
pyroge/connection/transport/tcp/tcp_intermediate.py
pyroge/connection/transport/tcp/tcp_intermediate_o.py
pyroge/crypto/__init__.py
pyroge/crypto/aes.py
pyroge/crypto/mtproto.py
pyroge/crypto/prime.py
pyroge/crypto/rsa.py
pyroge/enums/__init__.py
pyroge/enums/auto_name.py
pyroge/enums/chat_action.py
pyroge/enums/chat_event_action.py
pyroge/enums/chat_member_status.py
pyroge/enums/chat_members_filter.py
pyroge/enums/chat_type.py
pyroge/enums/message_entity_type.py
pyroge/enums/message_media_type.py
pyroge/enums/message_service_type.py
pyroge/enums/messages_filter.py
pyroge/enums/next_code_type.py
pyroge/enums/parse_mode.py
pyroge/enums/poll_type.py
