Metadata-Version: 2.1
Name: pyroge
Version: 0.0.1.dev1
Summary: pyroge - Telegram MTProto API Client Library for Python.
Home-page: https://github.com/vckyou/pyroge
Author: vckyou
Author-email: viicky.auliaz@gmail.com
License: GNU Lesser General Public License v3.0 (LGPL-3.0)
Project-URL: Bug Tracker, https://github.com/vckyou/pyroge/issues
Project-URL: Documentation, https://pyroge.tech
Project-URL: Source Code, https://github.com/vckyou/pyroge
Classifier: Programming Language :: Python :: 3
Classifier: Programming Language :: Python :: 3.8
Classifier: Programming Language :: Python :: 3.9
Classifier: Programming Language :: Python :: 3.10
Classifier: License :: OSI Approved :: GNU General Public License v3 (GPLv3)
Classifier: Operating System :: OS Independent
Requires-Python: ~=3.7
License-File: LICENSE
License-File: NOTICE
